mobster/__init__.py
mobster/artifact.py
mobster/cli.py
mobster/cmd/__init__.py
mobster/cmd/augment/__init__.py
mobster/cmd/augment/handlers.py
mobster/cmd/base.py
mobster/cmd/delete/__init__.py
mobster/cmd/delete/delete_tpa.py
mobster/cmd/download/__init__.py
mobster/cmd/download/download_tpa.py
mobster/cmd/generate/__init__.py
mobster/cmd/generate/base.py
mobster/cmd/generate/modelcar.py
mobster/cmd/generate/oci_artifact.py
mobster/cmd/generate/oci_image/__init__.py
mobster/cmd/generate/oci_image/add_image.py
mobster/cmd/generate/oci_image/base_images_dockerfile.py
mobster/cmd/generate/oci_image/constants.py
mobster/cmd/generate/oci_image/contextual_parent_content.py
mobster/cmd/generate/oci_image/cyclonedx_wrapper.py
mobster/cmd/generate/oci_image/spdx_utils.py
mobster/cmd/generate/oci_index.py
mobster/cmd/generate/pko_package.py
mobster/cmd/generate/product.py
mobster/cmd/upload/__init__.py
mobster/cmd/upload/model.py
mobster/cmd/upload/oidc.py
mobster/cmd/upload/tpa.py
mobster/cmd/upload/upload.py
mobster/error.py
mobster/image.py
mobster/log.py
mobster/main.py
mobster/oci/__init__.py
mobster/oci/artifact.py
mobster/oci/cosign.py
mobster/regenerate/__init__.py
mobster/regenerate/base.py
mobster/regenerate/component.py
mobster/regenerate/product.py
mobster/release.py
mobster/sbom/__init__.py
mobster/sbom/cyclonedx.py
mobster/sbom/merge.py
mobster/sbom/spdx.py
mobster/tekton/__init__.py
mobster/tekton/artifact.py
mobster/tekton/common.py
mobster/tekton/component.py
mobster/tekton/product.py
mobster/tekton/s3.py
mobster/utils.py
mobster-1.1.0.dist-info/METADATA
mobster-1.1.0.dist-info/WHEEL
mobster-1.1.0.dist-info/entry_points.txt
mobster-1.1.0.dist-info/licenses/LICENSE
mobster-1.1.0.dist-info/RECORD
