Metadata-Version: 2.4
Name: mobster
Version: 1.1.0
Summary: A tool for generating and managing Software Bill of Materials (SBOM).
License: Apache-2.0
License-File: LICENSE
Keywords: sbom,spdx,cyclonedx,security
Author: Ales Raszka
Author-email: araszka@redhat.com
Requires-Python: >=3.10,<4.0
Classifier: Development Status :: 4 - Beta
Classifier: Intended Audience :: Developers
Classifier: License :: OSI Approved :: Apache Software License
Classifier: Natural Language :: English
Classifier: Programming Language :: Python :: 3.10
Classifier: Programming Language :: Python :: 3.11
Classifier: Programming Language :: Python :: 3.12
Classifier: Programming Language :: Python :: 3.13
Classifier: Topic :: Software Development :: Libraries
Classifier: Topic :: Software Development :: Libraries :: Python Modules
Classifier: Topic :: Security
Requires-Dist: aioboto3 (>=15.2.0,<15.3.0)
Requires-Dist: aiofiles (>=24.1.0,<25.0.0)
Requires-Dist: cyclonedx-python-lib (==9.1.0)
Requires-Dist: httpx (>=0.28.1,<0.29.0)
Requires-Dist: packageurl-python (>=0.16.0,<0.17.0)
Requires-Dist: pydantic (>=2.11.4,<3.0.0)
Requires-Dist: python-dateutil (>=2.9.0.post0,<3.0.0)
Requires-Dist: spdx-tools (>=0.8.3,<0.9.0)
Project-URL: Repository, https://github.com/konflux-ci/mobster
